taulu-2.0.3.dist-info/METADATA
taulu-2.0.3.dist-info/WHEEL
taulu-2.0.3.dist-info/entry_points.txt
taulu/__init__.py
taulu/_core.pyi
taulu/_core.pypy39-pp73-ppc_64-linux-gnu.so
taulu/constants.py
taulu/decorators.py
taulu/error.py
taulu/grid.py
taulu/header_aligner.py
taulu/header_template.py
taulu/img_util.py
taulu/main.py
taulu/py.typed
taulu/split.py
taulu/table_indexer.py
taulu/taulu.py
taulu/torch/__init__.py
taulu/torch/data.py
taulu/torch/model.py
taulu/torch/run.py
taulu/torch/train.py
taulu/types.py
taulu-2.0.3.dist-info/RECORD
