Metadata-Version: 2.4
Name: taulu
Version: 2.0.3
Requires-Dist: matplotlib>=3.10.6
Requires-Dist: numpy>=2.2.4
Requires-Dist: opencv-python>=4.11.0.86
Requires-Dist: pandas>=2.2.3
Requires-Dist: scikit-image>=0.25.2
Requires-Dist: scipy>=1.15.2
Requires-Dist: pillow>=11.3.0 ; extra == 'torch'
Provides-Extra: torch
Summary: Segment a table from an image
Requires-Python: >=3.10, <3.14
